{"132632676225122304":{"oldMessage":"","newMessage":"","timestamp":null,"authorName":"R. Danny","iconUrl":"https://discordapp.com/api/v6/users/80528701850124288/avatars/1d89840ad386ee98aa5070315f018b3a.jpg"},"110373943822540800":{"oldMessage":"https://light-theme-hurts.my-ey.es/a47e95.png","newMessage":"https://light-theme-hurts.my-ey.es/a47e95.png","timestamp":null,"authorName":"Vex","iconUrl":"https://discordapp.com/api/v6/users/118547889931812868/avatars/b19f03e15ff234b04f09bc65f9e2ab38.jpg"},"119222314964353025":{"oldMessage":"","newMessage":"","timestamp":null,"authorName":"FlexBot","iconUrl":"https://discordapp.com/api/v6/users/152172984373608449/avatars/778eb40575f8b68736ebaaf19dded529.jpg"},"124622509881425920":{"oldMessage":"**Kick** | Case 1436\n**User**: PreFixx#9386 (272295201543028736)\nResponsible moderator, please do `!reason 1436 <reason>`","newMessage":"**Kick** | Case 1436\n**User**: PreFixx#9386 (272295201543028736)\n**Reason**: no ads\n**Responsible Moderator**: AlexFlipnote#3690","timestamp":1486906638803,"authorName":"Pollr","iconUrl":"https://discordapp.com/api/v6/users/168169809303961600/avatars/6c72661597784fb5431e7a5854b1c31b.jpg"},"113743192305827841":{"oldMessage":"📖 Profile for **Bob Pony** #1488:\n**YouTube**: https://www.youtube.com/channel/UCAZzz2Dd9Xh6vTjNcxhqPZw\n**Timezone**: UTC-5","newMessage":"📖 Profile for **Bob Pony** #1488:\n**YouTube**: https://www.youtube.com/channel/UCAZzz2Dd9Xh6vTjNcxhqPZw\n**Timezone**: UTC-5","timestamp":null,"authorName":"Spectra","iconUrl":"https://discordapp.com/api/v6/users/135251434445733888/avatars/7f51498b5311f53ee2c5077fa5aac7b4.jpg"},"199537212348432384":{"oldMessage":"He ain't pope","newMessage":"She ain't pope","timestamp":1486907742576,"authorName":"Ice Cat | Edgy Weeb","iconUrl":"https://discordapp.com/api/v6/users/251677891065151488/avatars/27c7cdd3626d2efbf72fe9f68afd3297.jpg"},"270177433209143296":{"oldMessage":"","newMessage":"","timestamp":null,"authorName":"Harmonbot","iconUrl":"https://cdn.discordapp.com/avatars/160677293252018177/6ff4fe83afed17703bfb673fe5c23984.jpg?size=1024"},"249864808126480384":{"oldMessage":"Just walking in the park with my pet snake.","newMessage":"Just slithering in the park with my pet snake.","timestamp":1486894135745,"authorName":"Mr. Hexagon","iconUrl":"https://discordapp.com/api/v6/users/234374513175953408/avatars/d6e79cf89ffbcd6b3bcdd523d652aec4.jpg"},"110374153562886144":{"oldMessage":"","newMessage":"","timestamp":null,"authorName":"Arraybot","iconUrl":"https://discordapp.com/api/v6/users/177735619668213760/avatars/fd7d481c8e83e9efbd038c55adeae677.jpg"},"271809545435611136":{"oldMessage":"In the jacket he wor","newMessage":"In the jacket he wore","timestamp":1486348480686,"authorName":"DanielDawn","iconUrl":"https://cdn.discordapp.com/avatars/212982478225408000/d87eda69effeb253334061f6ae631753.jpg?size=1024"},"271814324295565314":{"oldMessage":"http://sta.sh/016z27pn12d7 http://sta.sh/02fbmq84izrv simplified colour tutorials","newMessage":"http://sta.sh/016z27pn12d7 http://sta.sh/02fbmq84izrv simplified colour tutorials","timestamp":1486421578731,"authorName":"アイーク","iconUrl":"https://cdn.discordapp.com/avatars/120852359676035072/87dc5825504db55452a51f1cb61fb975.jpg?size=1024"},"217745836094783488":{"oldMessage":"","newMessage":"","timestamp":null,"authorName":"LewdBot","iconUrl":"https://discordapp.com/api/v6/users/119482224713269248/avatars/120698611d393aae8c07dea7e182b9c8.jpg"},"265299510517825536":{"oldMessage":"","newMessage":"","timestamp":null,"authorName":"Terabyte","iconUrl":"https://cdn.discordapp.com/avatars/276551537210425344/f7790c72eb4e38a9067f1239e604a00a.jpg?size=1024"},"117018340114825217":{"oldMessage":"","newMessage":"","timestamp":null,"authorName":"Mr.Cat","iconUrl":"https://discordapp.com/api/v6/users/279725066789322752/avatars/35b0bb45e1264528e4e6f1b9bb69d598.jpg"},"277737031894040576":{"oldMessage":"⭐ **2** #general-talk ID: 277743230508990464","newMessage":"⭐ **2** #general-talk ID: 277743230508990464","timestamp":1486302172182,"authorName":"x³","iconUrl":"https://cdn.discordapp.com/avatars/181625814335488001/fac69b5c288fb54593fdd7a70684d64f.jpg?size=1024"},"276135489386446848":{"oldMessage":"Server IP: \n199.187.127.138:25920","newMessage":"Server IP: \n199.187.127.138:25920","timestamp":null,"authorName":"Dom","iconUrl":"https://cdn.discordapp.com/avatars/148978986045669378/c575b2b6bf62f31bc9d85bb735b8e794.jpg?size=1024"},"271677131627429888":{"oldMessage":"http://perfectpokemon.com/userfeedback/i-mimic-you.33219/add-feedback","newMessage":"http://perfectpokemon.com/userfeedback/i-mimic-you.33219/add-feedback","timestamp":null,"authorName":"I Mimic You!","iconUrl":"https://discordapp.com/api/v6/users/271672669781360643/avatars/86c7b798518db9e22df06faa80ffedd2.jpg"},"277822180912529408":{"oldMessage":"\\_\\_\\_\\_\\_\\_\\_\\_\\_\\_\\_\\_\\_\\_\\_\\_\\_\\_\\_\\_\\_\\_\\_\\_\\_\n\n**Pursuit**","newMessage":"\\_\\_\\_\\_\\_\\_\\_\\_\\_\\_\\_\\_\\_\\_\\_\\_\\_\\_\\_\\_\\_\\_\\_\\_\\_\n\n**Pursuit**","timestamp":null,"authorName":"Beheeyem","iconUrl":"https://cdn.discordapp.com/avatars/246647016111865856/d2a44eb15541a8d4247dec683573a306.jpg?size=1024"},"167622210331082753":{"oldMessage":"...........","newMessage":"........... wrong button 👏","timestamp":1486311841224,"authorName":"Luna","iconUrl":"https://cdn.discordapp.com/avatars/180731582049550336/a_1d717b1d77d2f23db2b301f69632873a.gif?size=1024"},"269182714228375553":{"oldMessage":"~~Him and I need to have an \"ab-off.\"","newMessage":"~~Him and I need to have an \"ab-off.\"~~","timestamp":1486320580485,"authorName":"Dom","iconUrl":"https://cdn.discordapp.com/avatars/148978986045669378/c575b2b6bf62f31bc9d85bb735b8e794.jpg?size=1024"},"240291349549678594":{"oldMessage":"See what you're doing now is designing a new move fora new ability","newMessage":"See what you're doing now is designing a new move for a new ability","timestamp":1486423535869,"authorName":"Ninmai700 | Raiden","iconUrl":"https://cdn.discordapp.com/avatars/176091402596253696/8c883b9823459775e208928b397a7e11.jpg?size=1024"},"277822702591410186":{"oldMessage":"Ho-Oh can also tank steal","newMessage":"Ho-Oh can also tank steel","timestamp":1486330522509,"authorName":"SnakeNote","iconUrl":"https://cdn.discordapp.com/avatars/220669910903160833/46b0adea758b8de9815e54e0a95ff3f0.jpg?size=1024"},"277994462008049664":{"oldMessage":"Entrangle(f): Ghost/Normal\nAbility 1: Cute Charm\nAbility 2: Rivalry\nHA: Freed","newMessage":"Entrangle(f): Ghost/Normal\nAbility 1: Cute Charm\nAbility 2: Rivalry\nHA: Freed","timestamp":null,"authorName":"Ninmai700 | Raiden","iconUrl":"https://cdn.discordapp.com/avatars/176091402596253696/e2c456c68c85c89bc09d2384f76f9109.jpg?size=1024"},"270085930566549505":{"oldMessage":"https://docs.google.com/document/d/1vAUPa4jaulYU0NlDXObPXmSx5FalMIFQpbeW3HjNetg/edit?usp=sharing","newMessage":"https://docs.google.com/document/d/1vAUPa4jaulYU0NlDXObPXmSx5FalMIFQpbeW3HjNetg/edit?usp=sharing","timestamp":null,"authorName":"Ninmai700 | Raiden","iconUrl":"https://cdn.discordapp.com/avatars/176091402596253696/8c883b9823459775e208928b397a7e11.jpg?size=1024"},"273686467816194048":{"oldMessage":"75/80/75/45/95/100","newMessage":"75/80/75/45/95/100","timestamp":1486355870231,"authorName":"Ninmai700 | Raiden","iconUrl":"https://cdn.discordapp.com/avatars/176091402596253696/e2c456c68c85c89bc09d2384f76f9109.jpg?size=1024"},"268617340826943500":{"oldMessage":"Destiny Scarf\n*Prevents all opposing Pokémon, even Ghost-types, from switching out. If the Pokémon using this move is knocked out on the same turn, the opponent that dealt the final blow will faint as well. Once an opponent has been hit with this move, it can no longer be used.*\nAccuracy:  95%, 85BP, 10PP\nType: Ghost, Category: Physical","newMessage":"Destiny Scarf\n*Prevents all opposing Pokémon, even Ghost-types, from switching out. If the Pokémon using this move is knocked out on the same turn, the opponent that dealt the final blow will faint as well. Once an opponent has been hit with this move, it can no longer be used.*\nAccuracy:  95%, 85BP, 5PP\nType: Ghost, Category: Physical","timestamp":1486381355239,"authorName":"Ninmai700 | Raiden","iconUrl":"https://cdn.discordapp.com/avatars/176091402596253696/e2c456c68c85c89bc09d2384f76f9109.jpg?size=1024"},"273305652867104768":{"oldMessage":"Want to invite me to your server? Use the link below!\n\nhttps://discordapp.com/oauth2/authorize?client_id=246647016111865856&scope=bot&permissions=67488832\n\nWant to join the /r/Pokemon Discord? Check out this link!\nhttps://discord.gg/pokemon\n\nThank you for using Beheeyem! ❤","newMessage":"Want to invite me to your server? Use the link below!\n\nhttps://discordapp.com/oauth2/authorize?client_id=246647016111865856&scope=bot&permissions=67488832\n\nWant to join the /r/Pokemon Discord? Check out this link!\nhttps://discord.gg/pokemon\n\nThank you for using Beheeyem! ❤","timestamp":null,"authorName":"Beheeyem","iconUrl":"https://discordapp.com/api/v6/users/246647016111865856/avatars/d2a44eb15541a8d4247dec683573a306.jpg"},"156994380505415681":{"oldMessage":":black_square_button: **Wound Reflection** {5}{B}\nEnchantment\nAt the beginning of each end step, each opponent loses life equal to the life he or she lost this turn. (Damage causes loss of life.)\nFormats: Commander, Legacy, Modern, Vintage\nSHM\nhttp://magiccards.info/query?q=!Wound%20Reflection","newMessage":":black_square_button: **Wound Reflection** {5}{B}\nEnchantment\nAt the beginning of each end step, each opponent loses life equal to the life he or she lost this turn. (Damage causes loss of life.)\nFormats: Commander, Legacy, Modern, Vintage\nSHM\nhttp://magiccards.info/query?q=!Wound%20Reflection","timestamp":null,"authorName":"judgebot","iconUrl":"https://discordapp.com/api/v6/users/240537940378386442/avatars/8eb5f47d84cc85193fbfbeaca23f369f.jpg"},"280198751057084416":{"oldMessage":"https://github.com/daniel-lawrence-lu/discord-woofbot.git","newMessage":"https://github.com/daniel-lawrence-lu/discord-woofbot.git","timestamp":null,"authorName":"CapnCheesy","iconUrl":"https://discordapp.com/api/v6/users/172828887498096641/avatars/7fe2795b030c5384b08f586663e6b63f.jpg"},"263047972529373196":{"oldMessage":"https://cdn.discordapp.com/attachments/172558502928187393/279180309679964163/16473239_1140176576080604_4748732187565777795_n.jpg","newMessage":"https://cdn.discordapp.com/attachments/172558502928187393/279180309679964163/16473239_1140176576080604_4748732187565777795_n.jpg","timestamp":null,"authorName":"CapnCheesy","iconUrl":"https://discordapp.com/api/v6/users/172828887498096641/avatars/7fe2795b030c5384b08f586663e6b63f.jpg"},"252270702000996352":{"oldMessage":"Her das drives a fucking hummer","newMessage":"Her dad drives a fucking hummer","timestamp":1486886360157,"authorName":"-Just J-","iconUrl":"https://discordapp.com/api/v6/users/185800739090726913/avatars/a_c9179212327aea3357d1527b4f92db7c.jpg"},"274581589231403009":{"oldMessage":"***+ After:***","newMessage":"***+ After:***","timestamp":null,"authorName":"Salt","iconUrl":"https://discordapp.com/api/v6/users/244533925408538624/avatars/c065e42f93fd2c59331f88402f440c38.jpg"},"263699684013506560":{"oldMessage":"","newMessage":"","timestamp":null,"authorName":"FugBot","iconUrl":"https://discordapp.com/api/v6/users/277491212821331968/avatars/14bcb6b998308a858b7c26d53909a932.jpg"},"280084686456356864":{"oldMessage":"","newMessage":"","timestamp":1486911101567,"authorName":"NotSoBot","iconUrl":"https://discordapp.com/api/v6/users/170903342199865344/avatars/19ff683c7f255b62c21d9f33be9e97c6.jpg"}}
